[{"Symbol":"bnb","Date":"2017-11-10T00:00:00","Open":2.613891,"Close":2.345438,"Low":2.146952,"High":2.694973,"OpenCloseAverage":2.4796645,"LowHighAverage":2.4209625,"ExchangeCurrency":"aud","DataSource":"https://query1.finance.yahoo.com/v7/finance/download/BNB-AUD?period1=1420070400\u0026period2=1664928000\u0026interval=1d\u0026events=history\u0026includeAdjustedClose=true","LookupOptional":false},{"Symbol":"bnb","Date":"2017-11-11T00:00:00","Open":2.331654,"Close":2.180486,"Low":2.107153,"High":2.503263,"OpenCloseAverage":2.256070,"LowHighAverage":2.305208,"ExchangeCurrency":"aud","DataSource":"https://query1.finance.yahoo.com/v7/finance/download/BNB-AUD?period1=1420070400\u0026period2=1664928000\u0026interval=1d\u0026events=history\u0026includeAdjustedClose=true","LookupOptional":false},{"Symbol":"bnb","Date":"2017-11-12T00:00:00","Open":2.178423,"Close":1.987562,"Low":1.909098,"High":2.183527,"OpenCloseAverage":2.0829925,"LowHighAverage":2.0463125,"ExchangeCurrency":"aud","DataSource":"https://query1.finance.yahoo.com/v7/finance/download/BNB-AUD?period1=1420070400\u0026period2=1664928000\u0026interval=1d\u0026events=history\u0026includeAdjustedClose=true","LookupOptional":false},{"Symbol":"bnb","Date":"2017-11-13T00:00:00","Open":1.995828,"Close":2.215156,"Low":1.984569,"High":2.268593,"OpenCloseAverage":2.105492,"LowHighAverage":2.126581,"ExchangeCurrency":"aud","DataSource":"https://query1.finance.yahoo.com/v7/finance/download/BNB-AUD?period1=1420070400\u0026period2=1664928000\u0026interval=1d\u0026events=history\u0026includeAdjustedClose=true","LookupOptional":false},{"Symbol":"bnb","Date":"2017-11-14T00:00:00","Open":2.218650,"Close":2.087534,"Low":2.055400,"High":2.273212,"OpenCloseAverage":2.153092,"LowHighAverage":2.164306,"ExchangeCurrency":"aud","DataSource":"https://query1.finance.yahoo.com/v7/finance/download/BNB-AUD?period1=1420070400\u0026period2=1664928000\u0026interval=1d\u0026events=history\u0026includeAdjustedClose=true","LookupOptional":false},{"Symbol":"bnb","Date":"2017-11-15T00:00:00","Open":2.081229,"Close":2.016403,"Low":1.974518,"High":2.143490,"OpenCloseAverage":2.048816,"LowHighAverage":2.059004,"ExchangeCurrency":"aud","DataSource":"https://query1.finance.yahoo.com/v7/finance/download/BNB-AUD?period1=1420070400\u0026period2=1664928000\u0026interval=1d\u0026events=history\u0026includeAdjustedClose=true","LookupOptional":false},{"Symbol":"bnb","Date":"2017-11-16T00:00:00","Open":2.050316,"Close":2.079768,"Low":2.023555,"High":2.214613,"OpenCloseAverage":2.065042,"LowHighAverage":2.119084,"ExchangeCurrency":"aud","DataSource":"https://query1.finance.yahoo.com/v7/finance/download/BNB-AUD?period1=1420070400\u0026period2=1664928000\u0026interval=1d\u0026events=history\u0026includeAdjustedClose=true","LookupOptional":false},{"Symbol":"bnb","Date":"2017-11-17T00:00:00","Open":2.082575,"Close":1.996510,"Low":1.976603,"High":2.086290,"OpenCloseAverage":2.0395425,"LowHighAverage":2.0314465,"ExchangeCurrency":"aud","DataSource":"https://query1.finance.yahoo.com/v7/finance/download/BNB-AUD?period1=1420070400\u0026period2=1664928000\u0026interval=1d\u0026events=history\u0026includeAdjustedClose=true","LookupOptional":false},{"Symbol":"bnb","Date":"2017-11-18T00:00:00","Open":1.997832,"Close":2.213258,"Low":1.980476,"High":2.216497,"OpenCloseAverage":2.105545,"LowHighAverage":2.0984865,"ExchangeCurrency":"aud","DataSource":"https://query1.finance.yahoo.com/v7/finance/download/BNB-AUD?period1=1420070400\u0026period2=1664928000\u0026interval=1d\u0026events=history\u0026includeAdjustedClose=true","LookupOptional":false},{"Symbol":"bnb","Date":"2017-11-19T00:00:00","Open":2.211976,"Close":2.136878,"Low":2.074633,"High":2.248817,"OpenCloseAverage":2.174427,"LowHighAverage":2.161725,"ExchangeCurrency":"aud","DataSource":"https://query1.finance.yahoo.com/v7/finance/download/BNB-AUD?period1=1420070400\u0026period2=1664928000\u0026interval=1d\u0026events=history\u0026includeAdjustedClose=true","LookupOptional":false},{"Symbol":"bnb","Date":"2017-11-20T00:00:00","Open":2.152529,"Close":2.150735,"Low":2.058230,"High":2.199245,"OpenCloseAverage":2.151632,"LowHighAverage":2.1287375,"ExchangeCurrency":"aud","DataSource":"https://query1.finance.yahoo.com/v7/finance/download/BNB-AUD?period1=1420070400\u0026period2=1664928000\u0026interval=1d\u0026events=history\u0026includeAdjustedClose=true","LookupOptional":false},{"Symbol":"bnb","Date":"2017-11-21T00:00:00","Open":2.195379,"Close":2.075501,"Low":2.046263,"High":2.197074,"OpenCloseAverage":2.135440,"LowHighAverage":2.1216685,"ExchangeCurrency":"aud","DataSource":"https://query1.finance.yahoo.com/v7/finance/download/BNB-AUD?period1=1420070400\u0026period2=1664928000\u0026interval=1d\u0026events=history\u0026includeAdjustedClose=true","LookupOptional":false},{"Symbol":"bnb","Date":"2017-11-22T00:00:00","Open":2.097165,"Close":2.117380,"Low":2.053275,"High":2.129459,"OpenCloseAverage":2.1072725,"LowHighAverage":2.091367,"ExchangeCurrency":"aud","DataSource":"https://query1.finance.yahoo.com/v7/finance/download/BNB-AUD?period1=1420070400\u0026period2=1664928000\u0026interval=1d\u0026events=history\u0026includeAdjustedClose=true","LookupOptional":false},{"Symbol":"bnb","Date":"2017-11-23T00:00:00","Open":2.115870,"Close":2.031348,"Low":2.016776,"High":2.125533,"OpenCloseAverage":2.073609,"LowHighAverage":2.0711545,"ExchangeCurrency":"aud","DataSource":"https://query1.finance.yahoo.com/v7/finance/download/BNB-AUD?period1=1420070400\u0026period2=1664928000\u0026interval=1d\u0026events=history\u0026includeAdjustedClose=true","LookupOptional":false},{"Symbol":"bnb","Date":"2017-11-24T00:00:00","Open":2.058670,"Close":2.256582,"Low":2.040105,"High":2.391512,"OpenCloseAverage":2.157626,"LowHighAverage":2.2158085,"ExchangeCurrency":"aud","DataSource":"https://query1.finance.yahoo.com/v7/finance/download/BNB-AUD?period1=1420070400\u0026period2=1664928000\u0026interval=1d\u0026events=history\u0026includeAdjustedClose=true","LookupOptional":false},{"Symbol":"bnb","Date":"2017-11-25T00:00:00","Open":2.255610,"Close":2.461731,"Low":2.225394,"High":2.571781,"OpenCloseAverage":2.3586705,"LowHighAverage":2.3985875,"ExchangeCurrency":"aud","DataSource":"https://query1.finance.yahoo.com/v7/finance/download/BNB-AUD?period1=1420070400\u0026period2=1664928000\u0026interval=1d\u0026events=history\u0026includeAdjustedClose=true","LookupOptional":false},{"Symbol":"bnb","Date":"2017-11-26T00:00:00","Open":2.489149,"Close":2.435125,"Low":2.399816,"High":2.542446,"OpenCloseAverage":2.462137,"LowHighAverage":2.471131,"ExchangeCurrency":"aud","DataSource":"https://query1.finance.yahoo.com/v7/finance/download/BNB-AUD?period1=1420070400\u0026period2=1664928000\u0026interval=1d\u0026events=history\u0026includeAdjustedClose=true","LookupOptional":false},{"Symbol":"bnb","Date":"2017-11-27T00:00:00","Open":2.458384,"Close":2.555208,"Low":2.343061,"High":2.560850,"OpenCloseAverage":2.506796,"LowHighAverage":2.4519555,"ExchangeCurrency":"aud","DataSource":"https://query1.finance.yahoo.com/v7/finance/download/BNB-AUD?period1=1420070400\u0026period2=1664928000\u0026interval=1d\u0026events=history\u0026includeAdjustedClose=true","LookupOptional":false},{"Symbol":"bnb","Date":"2017-11-28T00:00:00","Open":2.576078,"Close":2.520855,"Low":2.455040,"High":2.574724,"OpenCloseAverage":2.5484665,"LowHighAverage":2.514882,"ExchangeCurrency":"aud","DataSource":"https://query1.finance.yahoo.com/v7/finance/download/BNB-AUD?period1=1420070400\u0026period2=1664928000\u0026interval=1d\u0026events=history\u0026includeAdjustedClose=true","LookupOptional":false},{"Symbol":"bnb","Date":"2017-11-29T00:00:00","Open":2.530362,"Close":2.315001,"Low":2.222007,"High":2.713743,"OpenCloseAverage":2.4226815,"LowHighAverage":2.467875,"ExchangeCurrency":"aud","DataSource":"https://query1.finance.yahoo.com/v7/finance/download/BNB-AUD?period1=1420070400\u0026period2=1664928000\u0026interval=1d\u0026events=history\u0026includeAdjustedClose=true","LookupOptional":false},{"Symbol":"bnb","Date":"2017-11-30T00:00:00","Open":2.328099,"Close":2.640796,"Low":2.329639,"High":2.706183,"OpenCloseAverage":2.4844475,"LowHighAverage":2.517911,"ExchangeCurrency":"aud","DataSource":"https://query1.finance.yahoo.com/v7/finance/download/BNB-AUD?period1=1420070400\u0026period2=1664928000\u0026interval=1d\u0026events=history\u0026includeAdjustedClose=true","LookupOptional":false},{"Symbol":"bnb","Date":"2017-12-01T00:00:00","Open":2.640770,"Close":2.720765,"Low":2.541930,"High":2.819647,"OpenCloseAverage":2.6807675,"LowHighAverage":2.6807885,"ExchangeCurrency":"aud","DataSource":"https://query1.finance.yahoo.com/v7/finance/download/BNB-AUD?period1=1420070400\u0026period2=1664928000\u0026interval=1d\u0026events=history\u0026includeAdjustedClose=true","LookupOptional":false},{"Symbol":"bnb","Date":"2017-12-02T00:00:00","Open":2.729741,"Close":2.739072,"Low":2.624379,"High":2.780470,"OpenCloseAverage":2.7344065,"LowHighAverage":2.7024245,"ExchangeCurrency":"aud","DataSource":"https://query1.finance.yahoo.com/v7/finance/download/BNB-AUD?period1=1420070400\u0026period2=1664928000\u0026interval=1d\u0026events=history\u0026includeAdjustedClose=true","LookupOptional":false},{"Symbol":"bnb","Date":"2017-12-03T00:00:00","Open":2.740715,"Close":2.935614,"Low":2.699684,"High":3.129386,"OpenCloseAverage":2.8381645,"LowHighAverage":2.914535,"ExchangeCurrency":"aud","DataSource":"https://query1.finance.yahoo.com/v7/finance/download/BNB-AUD?period1=1420070400\u0026period2=1664928000\u0026interval=1d\u0026events=history\u0026includeAdjustedClose=true","LookupOptional":false},{"Symbol":"bnb","Date":"2017-12-04T00:00:00","Open":2.976262,"Close":3.277233,"Low":2.975086,"High":3.400224,"OpenCloseAverage":3.1267475,"LowHighAverage":3.187655,"ExchangeCurrency":"aud","DataSource":"https://query1.finance.yahoo.com/v7/finance/download/BNB-AUD?period1=1420070400\u0026period2=1664928000\u0026interval=1d\u0026events=history\u0026includeAdjustedClose=true","LookupOptional":false},{"Symbol":"bnb","Date":"2017-12-05T00:00:00","Open":3.290556,"Close":3.413521,"Low":3.290989,"High":3.576578,"OpenCloseAverage":3.3520385,"LowHighAverage":3.4337835,"ExchangeCurrency":"aud","DataSource":"https://query1.finance.yahoo.com/v7/finance/download/BNB-AUD?period1=1420070400\u0026period2=1664928000\u0026interval=1d\u0026events=history\u0026includeAdjustedClose=true","LookupOptional":false},{"Symbol":"bnb","Date":"2017-12-06T00:00:00","Open":3.393963,"Close":3.420156,"Low":3.100965,"High":3.664526,"OpenCloseAverage":3.4070595,"LowHighAverage":3.3827455,"ExchangeCurrency":"aud","DataSource":"https://query1.finance.yahoo.com/v7/finance/download/BNB-AUD?period1=1420070400\u0026period2=1664928000\u0026interval=1d\u0026events=history\u0026includeAdjustedClose=true","LookupOptional":false},{"Symbol":"bnb","Date":"2017-12-07T00:00:00","Open":3.369548,"Close":3.701664,"Low":3.299881,"High":3.876087,"OpenCloseAverage":3.535606,"LowHighAverage":3.587984,"ExchangeCurrency":"aud","DataSource":"https://query1.finance.yahoo.com/v7/finance/download/BNB-AUD?period1=1420070400\u0026period2=1664928000\u0026interval=1d\u0026events=history\u0026includeAdjustedClose=true","LookupOptional":false},{"Symbol":"bnb","Date":"2017-12-08T00:00:00","Open":3.683222,"Close":3.772215,"Low":3.009550,"High":3.824300,"OpenCloseAverage":3.7277185,"LowHighAverage":3.416925,"ExchangeCurrency":"aud","DataSource":"https://query1.finance.yahoo.com/v7/finance/download/BNB-AUD?period1=1420070400\u0026period2=1664928000\u0026interval=1d\u0026events=history\u0026includeAdjustedClose=true","LookupOptional":false},{"Symbol":"bnb","Date":"2017-12-09T00:00:00","Open":3.766018,"Close":3.478718,"Low":3.105477,"High":3.821082,"OpenCloseAverage":3.622368,"LowHighAverage":3.4632795,"ExchangeCurrency":"aud","DataSource":"https://query1.finance.yahoo.com/v7/finance/download/BNB-AUD?period1=1420070400\u0026period2=1664928000\u0026interval=1d\u0026events=history\u0026includeAdjustedClose=true","LookupOptional":false},{"Symbol":"bnb","Date":"2017-12-10T00:00:00","Open":3.546562,"Close":3.308513,"Low":2.947361,"High":3.592004,"OpenCloseAverage":3.4275375,"LowHighAverage":3.2696825,"ExchangeCurrency":"aud","DataSource":"https://query1.finance.yahoo.com/v7/finance/download/BNB-AUD?period1=1420070400\u0026period2=1664928000\u0026interval=1d\u0026events=history\u0026includeAdjustedClose=true","LookupOptional":false},{"Symbol":"bnb","Date":"2017-12-11T00:00:00","Open":3.348015,"Close":3.595444,"Low":3.327595,"High":3.751468,"OpenCloseAverage":3.4717295,"LowHighAverage":3.5395315,"ExchangeCurrency":"aud","DataSource":"https://query1.finance.yahoo.com/v7/finance/download/BNB-AUD?period1=1420070400\u0026period2=1664928000\u0026interval=1d\u0026events=history\u0026includeAdjustedClose=true","LookupOptional":false},{"Symbol":"bnb","Date":"2017-12-12T00:00:00","Open":3.621745,"Close":3.553607,"Low":3.465628,"High":3.675000,"OpenCloseAverage":3.587676,"LowHighAverage":3.570314,"ExchangeCurrency":"aud","DataSource":"https://query1.finance.yahoo.com/v7/finance/download/BNB-AUD?period1=1420070400\u0026period2=1664928000\u0026interval=1d\u0026events=history\u0026includeAdjustedClose=true","LookupOptional":false},{"Symbol":"bnb","Date":"2017-12-13T00:00:00","Open":3.556691,"Close":3.641500,"Low":3.395088,"High":3.779480,"OpenCloseAverage":3.5990955,"LowHighAverage":3.587284,"ExchangeCurrency":"aud","DataSource":"https://query1.finance.yahoo.com/v7/finance/download/BNB-AUD?period1=1420070400\u0026period2=1664928000\u0026interval=1d\u0026events=history\u0026includeAdjustedClose=true","LookupOptional":false},{"Symbol":"bnb","Date":"2017-12-14T00:00:00","Open":3.635391,"Close":4.121529,"Low":3.634369,"High":4.121529,"OpenCloseAverage":3.878460,"LowHighAverage":3.877949,"ExchangeCurrency":"aud","DataSource":"https://query1.finance.yahoo.com/v7/finance/download/BNB-AUD?period1=1420070400\u0026period2=1664928000\u0026interval=1d\u0026events=history\u0026includeAdjustedClose=true","LookupOptional":false},{"Symbol":"bnb","Date":"2017-12-15T00:00:00","Open":4.118867,"Close":5.227826,"Low":4.098617,"High":5.768602,"OpenCloseAverage":4.6733465,"LowHighAverage":4.9336095,"ExchangeCurrency":"aud","DataSource":"https://query1.finance.yahoo.com/v7/finance/download/BNB-AUD?period1=1420070400\u0026period2=1664928000\u0026interval=1d\u0026events=history\u0026includeAdjustedClose=true","LookupOptional":false},{"Symbol":"bnb","Date":"2017-12-16T00:00:00","Open":5.453257,"Close":6.102368,"Low":5.126112,"High":6.181855,"OpenCloseAverage":5.7778125,"LowHighAverage":5.6539835,"ExchangeCurrency":"aud","DataSource":"https://query1.finance.yahoo.com/v7/finance/download/BNB-AUD?period1=1420070400\u0026period2=1664928000\u0026interval=1d\u0026events=history\u0026includeAdjustedClose=true","LookupOptional":false},{"Symbol":"bnb","Date":"2017-12-17T00:00:00","Open":6.108504,"Close":7.530046,"Low":6.108504,"High":8.831018,"OpenCloseAverage":6.819275,"LowHighAverage":7.469761,"ExchangeCurrency":"aud","DataSource":"https://query1.finance.yahoo.com/v7/finance/download/BNB-AUD?period1=1420070400\u0026period2=1664928000\u0026interval=1d\u0026events=history\u0026includeAdjustedClose=true","LookupOptional":false},{"Symbol":"bnb","Date":"2017-12-18T00:00:00","Open":7.576717,"Close":7.328527,"Low":6.897819,"High":8.123949,"OpenCloseAverage":7.452622,"LowHighAverage":7.510884,"ExchangeCurrency":"aud","DataSource":"https://query1.finance.yahoo.com/v7/finance/download/BNB-AUD?period1=1420070400\u0026period2=1664928000\u0026interval=1d\u0026events=history\u0026includeAdjustedClose=true","LookupOptional":false},{"Symbol":"bnb","Date":"2017-12-19T00:00:00","Open":7.369176,"Close":7.570683,"Low":7.281430,"High":8.526993,"OpenCloseAverage":7.4699295,"LowHighAverage":7.9042115,"ExchangeCurrency":"aud","DataSource":"https://query1.finance.yahoo.com/v7/finance/download/BNB-AUD?period1=1420070400\u0026period2=1664928000\u0026interval=1d\u0026events=history\u0026includeAdjustedClose=true","LookupOptional":false},{"Symbol":"bnb","Date":"2017-12-20T00:00:00","Open":7.565848,"Close":6.748644,"Low":6.428420,"High":7.563870,"OpenCloseAverage":7.157246,"LowHighAverage":6.996145,"ExchangeCurrency":"aud","DataSource":"https://query1.finance.yahoo.com/v7/finance/download/BNB-AUD?period1=1420070400\u0026period2=1664928000\u0026interval=1d\u0026events=history\u0026includeAdjustedClose=true","LookupOptional":false},{"Symbol":"bnb","Date":"2017-12-21T00:00:00","Open":6.759987,"Close":6.722920,"Low":6.257832,"High":7.443710,"OpenCloseAverage":6.7414535,"LowHighAverage":6.850771,"ExchangeCurrency":"aud","DataSource":"https://query1.finance.yahoo.com/v7/finance/download/BNB-AUD?period1=1420070400\u0026period2=1664928000\u0026interval=1d\u0026events=history\u0026includeAdjustedClose=true","LookupOptional":false},{"Symbol":"bnb","Date":"2017-12-22T00:00:00","Open":6.755951,"Close":5.620415,"Low":4.555050,"High":6.762766,"OpenCloseAverage":6.188183,"LowHighAverage":5.658908,"ExchangeCurrency":"aud","DataSource":"https://query1.finance.yahoo.com/v7/finance/download/BNB-AUD?period1=1420070400\u0026period2=1664928000\u0026interval=1d\u0026events=history\u0026includeAdjustedClose=true","LookupOptional":false},{"Symbol":"bnb","Date":"2017-12-23T00:00:00","Open":5.696643,"Close":6.272534,"Low":5.583422,"High":6.655230,"OpenCloseAverage":5.9845885,"LowHighAverage":6.119326,"ExchangeCurrency":"aud","DataSource":"https://query1.finance.yahoo.com/v7/finance/download/BNB-AUD?period1=1420070400\u0026period2=1664928000\u0026interval=1d\u0026events=history\u0026includeAdjustedClose=true","LookupOptional":false},{"Symbol":"bnb","Date":"2017-12-24T00:00:00","Open":6.146260,"Close":6.855616,"Low":5.442190,"High":6.855616,"OpenCloseAverage":6.500938,"LowHighAverage":6.148903,"ExchangeCurrency":"aud","DataSource":"https://query1.finance.yahoo.com/v7/finance/download/BNB-AUD?period1=1420070400\u0026period2=1664928000\u0026interval=1d\u0026events=history\u0026includeAdjustedClose=true","LookupOptional":false},{"Symbol":"bnb","Date":"2017-12-25T00:00:00","Open":6.885318,"Close":8.495221,"Low":6.802098,"High":8.998862,"OpenCloseAverage":7.6902695,"LowHighAverage":7.900480,"ExchangeCurrency":"aud","DataSource":"https://query1.finance.yahoo.com/v7/finance/download/BNB-AUD?period1=1420070400\u0026period2=1664928000\u0026interval=1d\u0026events=history\u0026includeAdjustedClose=true","LookupOptional":false},{"Symbol":"bnb","Date":"2017-12-26T00:00:00","Open":8.494276,"Close":11.682520,"Low":8.407377,"High":13.744953,"OpenCloseAverage":10.088398,"LowHighAverage":11.076165,"ExchangeCurrency":"aud","DataSource":"https://query1.finance.yahoo.com/v7/finance/download/BNB-AUD?period1=1420070400\u0026period2=1664928000\u0026interval=1d\u0026events=history\u0026includeAdjustedClose=true","LookupOptional":false},{"Symbol":"bnb","Date":"2017-12-27T00:00:00","Open":11.973425,"Close":13.002702,"Low":10.922253,"High":14.544075,"OpenCloseAverage":12.4880635,"LowHighAverage":12.733164,"ExchangeCurrency":"aud","DataSource":"https://query1.finance.yahoo.com/v7/finance/download/BNB-AUD?period1=1420070400\u0026period2=1664928000\u0026interval=1d\u0026events=history\u0026includeAdjustedClose=true","LookupOptional":false},{"Symbol":"bnb","Date":"2017-12-28T00:00:00","Open":13.027531,"Close":11.961260,"Low":10.478693,"High":13.104228,"OpenCloseAverage":12.4943955,"LowHighAverage":11.7914605,"ExchangeCurrency":"aud","DataSource":"https://query1.finance.yahoo.com/v7/finance/download/BNB-AUD?period1=1420070400\u0026period2=1664928000\u0026interval=1d\u0026events=history\u0026includeAdjustedClose=true","LookupOptional":false},{"Symbol":"bnb","Date":"2017-12-29T00:00:00","Open":11.957680,"Close":11.290347,"Low":10.918046,"High":12.232008,"OpenCloseAverage":11.6240135,"LowHighAverage":11.575027,"ExchangeCurrency":"aud","DataSource":"https://query1.finance.yahoo.com/v7/finance/download/BNB-AUD?period1=1420070400\u0026period2=1664928000\u0026interval=1d\u0026events=history\u0026includeAdjustedClose=true","LookupOptional":false},{"Symbol":"bnb","Date":"2017-12-30T00:00:00","Open":11.170068,"Close":10.051288,"Low":9.214127,"High":11.230739,"OpenCloseAverage":10.610678,"LowHighAverage":10.222433,"ExchangeCurrency":"aud","DataSource":"https://query1.finance.yahoo.com/v7/finance/download/BNB-AUD?period1=1420070400\u0026period2=1664928000\u0026interval=1d\u0026events=history\u0026includeAdjustedClose=true","LookupOptional":false},{"Symbol":"bnb","Date":"2017-12-31T00:00:00","Open":9.951686,"Close":11.075516,"Low":9.882054,"High":11.327848,"OpenCloseAverage":10.513601,"LowHighAverage":10.604951,"ExchangeCurrency":"aud","DataSource":"https://query1.finance.yahoo.com/v7/finance/download/BNB-AUD?period1=1420070400\u0026period2=1664928000\u0026interval=1d\u0026events=history\u0026includeAdjustedClose=true","LookupOptional":false}]